wapiclient/__init__.py
wapiclient-0.1.0.dist-info/METADATA
wapiclient-0.1.0.dist-info/WHEEL
wapiclient-0.1.0.dist-info/RECORD
