Metadata-Version: 2.1
Name: wapiclient
Version: 0.1.0
Summary: WEDOS API client
License: MIT
Author: Jakub Dorňák
Author-email: jakub.dornak@qbsoftware.cz
Requires-Python: >=3.10,<4.0
Classifier: License :: OSI Approved :: MIT License
Classifier: Programming Language :: Python :: 3
Classifier: Programming Language :: Python :: 3.10
Classifier: Programming Language :: Python :: 3.11
Classifier: Programming Language :: Python :: 3.12
